<annotation>
	<folder>images</folder>
	<filename>car_030.png</filename>
	<path>C:\Users\kacpe\Desktop\object-detection-and-labeling-pytorch\dataset\images_selected\images\car_030.png</path>
	<source>
		<database>Unknown</database>
	</source>
	<size>
		<width>2848</width>
		<height>1600</height>
		<depth>3</depth>
	</size>
	<segmented>0</segmented>
	<object>
		<name>car</name>
		<pose>Unspecified</pose>
		<truncated>0</truncated>
		<difficult>0</difficult>
		<bndbox>
			<xmin>754</xmin>
			<ymin>1109</ymin>
			<xmax>1101</xmax>
			<ymax>1280</ymax>
		</bndbox>
	</object>
	<object>
		<name>car</name>
		<pose>Unspecified</pose>
		<truncated>0</truncated>
		<difficult>0</difficult>
		<bndbox>
			<xmin>1245</xmin>
			<ymin>1128</ymin>
			<xmax>1413</xmax>
			<ymax>1239</ymax>
		</bndbox>
	</object>
	<object>
		<name>car</name>
		<pose>Unspecified</pose>
		<truncated>0</truncated>
		<difficult>0</difficult>
		<bndbox>
			<xmin>1550</xmin>
			<ymin>1139</ymin>
			<xmax>1826</xmax>
			<ymax>1334</ymax>
		</bndbox>
	</object>
	<object>
		<name>car</name>
		<pose>Unspecified</pose>
		<truncated>0</truncated>
		<difficult>0</difficult>
		<bndbox>
			<xmin>1411</xmin>
			<ymin>1138</ymin>
			<xmax>1500</xmax>
			<ymax>1218</ymax>
		</bndbox>
	</object>
	<object>
		<name>car</name>
		<pose>Unspecified</pose>
		<truncated>0</truncated>
		<difficult>0</difficult>
		<bndbox>
			<xmin>1501</xmin>
			<ymin>1139</ymin>
			<xmax>1576</xmax>
			<ymax>1193</ymax>
		</bndbox>
	</object>
	<object>
		<name>car</name>
		<pose>Unspecified</pose>
		<truncated>0</truncated>
		<difficult>0</difficult>
		<bndbox>
			<xmin>1349</xmin>
			<ymin>1105</ymin>
			<xmax>1523</xmax>
			<ymax>1195</ymax>
		</bndbox>
	</object>
	<object>
		<name>car</name>
		<pose>Unspecified</pose>
		<truncated>0</truncated>
		<difficult>0</difficult>
		<bndbox>
			<xmin>1573</xmin>
			<ymin>1131</ymin>
			<xmax>1628</xmax>
			<ymax>1185</ymax>
		</bndbox>
	</object>
</annotation>
