<annotation>
	<folder>images</folder>
	<filename>car_425.png</filename>
	<path>C:\Users\kubac\Desktop\dataset\images_selected\images\car_425.png</path>
	<source>
		<database>Unknown</database>
	</source>
	<size>
		<width>2848</width>
		<height>1600</height>
		<depth>3</depth>
	</size>
	<segmented>0</segmented>
	<object>
		<name>car</name>
		<pose>Unspecified</pose>
		<truncated>0</truncated>
		<difficult>0</difficult>
		<bndbox>
			<xmin>1226</xmin>
			<ymin>1007</ymin>
			<xmax>1843</xmax>
			<ymax>1488</ymax>
		</bndbox>
	</object>
	<object>
		<name>car</name>
		<pose>Unspecified</pose>
		<truncated>0</truncated>
		<difficult>0</difficult>
		<bndbox>
			<xmin>776</xmin>
			<ymin>957</ymin>
			<xmax>1317</xmax>
			<ymax>1324</ymax>
		</bndbox>
	</object>
	<object>
		<name>car</name>
		<pose>Unspecified</pose>
		<truncated>0</truncated>
		<difficult>0</difficult>
		<bndbox>
			<xmin>1202</xmin>
			<ymin>1009</ymin>
			<xmax>1414</xmax>
			<ymax>1192</ymax>
		</bndbox>
	</object>
	<object>
		<name>car</name>
		<pose>Unspecified</pose>
		<truncated>0</truncated>
		<difficult>0</difficult>
		<bndbox>
			<xmin>1888</xmin>
			<ymin>892</ymin>
			<xmax>2249</xmax>
			<ymax>1190</ymax>
		</bndbox>
	</object>
	<object>
		<name>car</name>
		<pose>Unspecified</pose>
		<truncated>0</truncated>
		<difficult>0</difficult>
		<bndbox>
			<xmin>1528</xmin>
			<ymin>812</ymin>
			<xmax>1864</xmax>
			<ymax>1186</ymax>
		</bndbox>
	</object>
</annotation>
