<annotation>
	<folder>images</folder>
	<filename>car_002.png</filename>
	<path>C:\Users\kacpe\Desktop\object-detection-and-labeling-pytorch\dataset\images_selected\images\car_002.png</path>
	<source>
		<database>Unknown</database>
	</source>
	<size>
		<width>2848</width>
		<height>1600</height>
		<depth>3</depth>
	</size>
	<segmented>0</segmented>
	<object>
		<name>car</name>
		<pose>Unspecified</pose>
		<truncated>0</truncated>
		<difficult>0</difficult>
		<bndbox>
			<xmin>1486</xmin>
			<ymin>1109</ymin>
			<xmax>1717</xmax>
			<ymax>1305</ymax>
		</bndbox>
	</object>
	<object>
		<name>car</name>
		<pose>Unspecified</pose>
		<truncated>0</truncated>
		<difficult>0</difficult>
		<bndbox>
			<xmin>1354</xmin>
			<ymin>1061</ymin>
			<xmax>1491</xmax>
			<ymax>1218</ymax>
		</bndbox>
	</object>
	<object>
		<name>car</name>
		<pose>Unspecified</pose>
		<truncated>0</truncated>
		<difficult>0</difficult>
		<bndbox>
			<xmin>926</xmin>
			<ymin>1018</ymin>
			<xmax>1224</xmax>
			<ymax>1195</ymax>
		</bndbox>
	</object>
	<object>
		<name>car</name>
		<pose>Unspecified</pose>
		<truncated>0</truncated>
		<difficult>0</difficult>
		<bndbox>
			<xmin>71</xmin>
			<ymin>1043</ymin>
			<xmax>305</xmax>
			<ymax>1170</ymax>
		</bndbox>
	</object>
</annotation>
