<annotation>
	<folder>images</folder>
	<filename>car_351.png</filename>
	<path>C:\Users\kubac\Desktop\dataset\images_selected\images\car_351.png</path>
	<source>
		<database>Unknown</database>
	</source>
	<size>
		<width>2848</width>
		<height>1600</height>
		<depth>3</depth>
	</size>
	<segmented>0</segmented>
	<object>
		<name>car</name>
		<pose>Unspecified</pose>
		<truncated>0</truncated>
		<difficult>0</difficult>
		<bndbox>
			<xmin>1669</xmin>
			<ymin>1061</ymin>
			<xmax>1789</xmax>
			<ymax>1125</ymax>
		</bndbox>
	</object>
</annotation>
